README.md
setup.py
setup/__init__.py
setup/asgi.py
setup/settings.py
setup/urls.py
setup/wsgi.py
stativiz/__init__.py
stativiz/agent.py
stativiz.egg-info/PKG-INFO
stativiz.egg-info/SOURCES.txt
stativiz.egg-info/dependency_links.txt
stativiz.egg-info/requires.txt
stativiz.egg-info/top_level.txt
stativo/__init__.py
stativo/admin.py
stativo/apps.py
stativo/firebase_agent.py
stativo/models.py
stativo/serializers.py
stativo/tests.py
stativo/urls.py
stativo/views.py
stativo/migrations/__init__.py